{
  "status": "SUCCESS",
  "errorCode": null,
  "data": {
    "content": [
      {
        "postId": 1,
        "title": "첫번째 글입니다",
        "content": "첫번째 글 내용입니다첫번째 글 내용입니다첫번째 글 내용입니다첫번째 글 내용입니다첫번째 글 내용입니다첫번째 글 내용입니다첫번째 글 내용입니다첫번째 글 내용입니다첫번째 글 내용입니다첫번째 글 내용입니다첫번째 글 내용입니다첫번째 글 내용입니다첫번째 글 내용입니다첫번째 글 내용입니다첫번째 글 내용입니다첫번째 글 내용입니다첫번째 글 내용입니다첫번째 글 내용입니다첫번째 글 내용입니다첫번째 글 내용입니다첫번째 글 내용입니다첫번째 글 내용입니다첫번째 글 내용입니다첫번째 글 내용입니다첫번째 글 내용입니다첫번째 글 내용입니다첫번째 글 내용입니다첫번째 글 내용입니다첫번째 글 내용입니다첫번째 글 내용입니다첫번째 글 내용입니다첫번째 글 내용입니다",
        "image": ["/community/userImg.jpeg", "/community/userImg.jpeg"],
        "category": "OWNER",
        "tag": "첫번째태그",
        "createdAt": "2024-05-13T08:30:00Z",
        "viewCount": 10,
        "likeCount": 10,
        "commentCount": 10,
        "writer": {
          "profile": "/community/userImg.jpeg",
          "job": "FINANCE",
          "nickname": "닉네임_1"
        },
        "isWished": false,
        "isWriter": false
      },
      {
        "postId": 2,
        "title": "두번째 글입니다",
        "content": "두번째 글 내용입니다첫번째 글 내용입니다첫번째 글 내용입니다첫번째 글 내용입니다첫번째 글 내용입니다첫번째 글 내용입니다첫번째 글 내용입니다첫번째 글 내용입니다첫번째 글 내용입니다첫번째 글 내용입니다첫번째 글 내용입니다첫번째 글 내용입니다첫번째 글 내용입니다첫번째 글 내용입니다첫번째 글 내용입니다첫번째 글 내용입니다첫번째 글 내용입니다첫번째 글 내용입니다첫번째 글 내용입니다첫번째 글 내용입니다첫번째 글 내용입니다첫번째 글 내용입니다첫번째 글 내용입니다첫번째 글 내용입니다첫번째 글 내용입니다첫번째 글 내용입니다첫번째 글 내용입니다첫번째 글 내용입니다첫번째 글 내용입니다첫번째 글 내용입니다첫번째 글 내용입니다첫번째 글 내용입니다",
        "image": ["/community/userImg.jpeg", "/community/userImg.jpeg"],
        "category": "OWNER",
        "tag": "두번째태그",
        "createdAt": "2024-05-13T08:30:00Z",
        "viewCount": 10,
        "likeCount": 10,
        "commentCount": 10,
        "writer": {
          "profile": "/community/userImg.jpeg",
          "job": "FINANCE",
          "nickname": "닉네임_2"
        },
        "isWished": false,
        "isWriter": false
      },
      {
        "postId": 3,
        "title": "세번째 글입니다",
        "content": "세번째 글 내용입니다첫번째 글 내용입니다첫번째 글 내용입니다첫번째 글 내용입니다첫번째 글 내용입니다첫번째 글 내용입니다첫번째 글 내용입니다첫번째 글 내용입니다첫번째 글 내용입니다첫번째 글 내용입니다첫번째 글 내용입니다첫번째 글 내용입니다첫번째 글 내용입니다첫번째 글 내용입니다첫번째 글 내용입니다첫번째 글 내용입니다첫번째 글 내용입니다첫번째 글 내용입니다첫번째 글 내용입니다첫번째 글 내용입니다첫번째 글 내용입니다첫번째 글 내용입니다첫번째 글 내용입니다첫번째 글 내용입니다첫번째 글 내용입니다첫번째 글 내용입니다첫번째 글 내용입니다첫번째 글 내용입니다첫번째 글 내용입니다첫번째 글 내용입니다첫번째 글 내용입니다첫번째 글 내용입니다",
        "image": ["/community/userImg.jpeg", "/community/userImg.jpeg"],
        "category": "OWNER",
        "tag": "글 태그",
        "createdAt": "2024-05-13T08:30:00Z",
        "viewCount": 10,
        "likeCount": 10,
        "commentCount": 10,
        "writer": {
          "profile": "/community/userImg.jpeg",
          "job": "FINANCE",
          "nickname": "닉네임_3"
        },
        "isWished": false,
        "isWriter": false
      },
      {
        "postId": 4,
        "title": "네번째 글입니다",
        "content": "네번째 글 내용입니다첫번째 글 내용입니다첫번째 글 내용입니다첫번째 글 내용입니다첫번째 글 내용입니다첫번째 글 내용입니다첫번째 글 내용입니다첫번째 글 내용입니다첫번째 글 내용입니다첫번째 글 내용입니다첫번째 글 내용입니다첫번째 글 내용입니다첫번째 글 내용입니다첫번째 글 내용입니다첫번째 글 내용입니다첫번째 글 내용입니다첫번째 글 내용입니다첫번째 글 내용입니다첫번째 글 내용입니다첫번째 글 내용입니다첫번째 글 내용입니다첫번째 글 내용입니다첫번째 글 내용입니다첫번째 글 내용입니다첫번째 글 내용입니다첫번째 글 내용입니다첫번째 글 내용입니다첫번째 글 내용입니다첫번째 글 내용입니다첫번째 글 내용입니다첫번째 글 내용입니다첫번째 글 내용입니다",
        "image": ["/community/userImg.jpeg", "/community/userImg.jpeg"],
        "category": "OWNER",
        "tag": "글 태그",
        "createdAt": "2024-05-13T08:30:00Z",
        "viewCount": 10,
        "likeCount": 10,
        "commentCount": 10,
        "writer": {
          "profile": "/community/userImg.jpeg",
          "job": "FINANCE",
          "nickname": "닉네임_4"
        },
        "isWished": false,
        "isWriter": false
      },
      {
        "postId": 5,
        "title": "5번째 글입니다",
        "content": "5번째 글 내용입니다첫번째 글 내용입니다첫번째 글 내용입니다첫번째 글 내용입니다첫번째 글 내용입니다첫번째 글 내용입니다첫번째 글 내용입니다첫번째 글 내용입니다첫번째 글 내용입니다첫번째 글 내용입니다첫번째 글 내용입니다첫번째 글 내용입니다첫번째 글 내용입니다첫번째 글 내용입니다첫번째 글 내용입니다첫번째 글 내용입니다첫번째 글 내용입니다첫번째 글 내용입니다첫번째 글 내용입니다첫번째 글 내용입니다첫번째 글 내용입니다첫번째 글 내용입니다첫번째 글 내용입니다첫번째 글 내용입니다첫번째 글 내용입니다첫번째 글 내용입니다첫번째 글 내용입니다첫번째 글 내용입니다첫번째 글 내용입니다첫번째 글 내용입니다첫번째 글 내용입니다첫번째 글 내용입니다",
        "image": ["/community/userImg.jpeg", "/community/userImg.jpeg"],
        "category": "OWNER",
        "tag": "글 태그",
        "createdAt": "2024-05-13T08:30:00Z",
        "viewCount": 10,
        "likeCount": 10,
        "commentCount": 10,
        "writer": {
          "profile": "/community/userImg.jpeg",
          "job": "FINANCE",
          "nickname": "닉네임_5"
        },
        "isWished": false,
        "isWriter": false
      }
    ],
    "hasNext": true
  },
  "message": null
}
